pbshm/ietools/__init__.py
pbshm/ietools/routes.py
pbshm/ietools/tools.py
pbshm/ietools/files/blank-structure.json
pbshm/ietools/templates/edit-model.html
pbshm/ietools/templates/list-models.html
pbshm/ietools/templates/validate-model.html
pbshm_ie_toolbox-0.1.4.dist-info/licenses/LICENSE
pbshm_ie_toolbox-0.1.4.dist-info/METADATA
pbshm_ie_toolbox-0.1.4.dist-info/WHEEL
pbshm_ie_toolbox-0.1.4.dist-info/top_level.txt
pbshm_ie_toolbox-0.1.4.dist-info/RECORD
