Metadata-Version: 2.4
Name: pbshm-ie-toolbox
Version: 0.1.4
Summary: PBSHM IE Model Toolbox
Author-email: Dan Brennan <d.s.brennan@sheffield.ac.uk>
License: MIT License
Project-URL: homepage, https://github.com/dsbrennan/ie-tools
Classifier: License :: OSI Approved :: MIT License
Classifier: Programming Language :: Python :: 3
Classifier: Framework :: Flask
Requires-Python: >=3.8.10
License-File: LICENSE
Requires-Dist: pbshm-core==1.1.6
Dynamic: license-file
